awslabs/__init__.py
awslabs/cdk_mcp_server/__init__.py
awslabs/cdk_mcp_server/server.py
awslabs/cdk_mcp_server/core/__init__.py
awslabs/cdk_mcp_server/core/resources.py
awslabs/cdk_mcp_server/core/search_utils.py
awslabs/cdk_mcp_server/core/server.py
awslabs/cdk_mcp_server/core/tools.py
awslabs/cdk_mcp_server/data/__init__.py
awslabs/cdk_mcp_server/data/cdk_nag_parser.py
awslabs/cdk_mcp_server/data/construct_descriptions.py
awslabs/cdk_mcp_server/data/genai_cdk_loader.py
awslabs/cdk_mcp_server/data/lambda_layer_parser.py
awslabs/cdk_mcp_server/data/lambda_powertools_loader.py
awslabs/cdk_mcp_server/data/schema_generator.py
awslabs/cdk_mcp_server/data/solutions_constructs_parser.py
awslabs/cdk_mcp_server/static/CDK_GENERAL_GUIDANCE.md
awslabs/cdk_mcp_server/static/CDK_NAG_GUIDANCE.md
awslabs/cdk_mcp_server/static/__init__.py
awslabs/cdk_mcp_server/static/lambda_powertools/bedrock.md
awslabs/cdk_mcp_server/static/lambda_powertools/cdk.md
awslabs/cdk_mcp_server/static/lambda_powertools/dependencies.md
awslabs/cdk_mcp_server/static/lambda_powertools/index.md
awslabs/cdk_mcp_server/static/lambda_powertools/insights.md
awslabs/cdk_mcp_server/static/lambda_powertools/logging.md
awslabs/cdk_mcp_server/static/lambda_powertools/metrics.md
awslabs/cdk_mcp_server/static/lambda_powertools/tracing.md
awslabs_cdk_mcp_server-1.0.12.dist-info/METADATA
awslabs_cdk_mcp_server-1.0.12.dist-info/WHEEL
awslabs_cdk_mcp_server-1.0.12.dist-info/entry_points.txt
awslabs_cdk_mcp_server-1.0.12.dist-info/licenses/LICENSE
awslabs_cdk_mcp_server-1.0.12.dist-info/licenses/NOTICE
awslabs_cdk_mcp_server-1.0.12.dist-info/RECORD
