Metadata-Version: 2.4
Name: awslabs.cdk-mcp-server
Version: 1.0.12
Summary: An AWS CDK MCP server that provides guidance on AWS Cloud Development Kit best practices, infrastructure as code patterns, and security compliance with CDK Nag. This server offers tools to validate infrastructure designs, explain CDK Nag rules, analyze suppressions, generate Bedrock Agent schemas, and discover Solutions Constructs patterns.
Project-URL: Homepage, https://awslabs.github.io/mcp/
Project-URL: Documentation, https://awslabs.github.io/mcp/servers/cdk-mcp-server/
Project-URL: Source, https://github.com/awslabs/mcp.git
Project-URL: Bug Tracker, https://github.com/awslabs/mcp/issues
Project-URL: Changelog, https://github.com/awslabs/mcp/blob/main/src/cdk-mcp-server/CHANGELOG.md
Author: Amazon Web Services
Author-email: AWSLabs MCP <203918161+awslabs-mcp@users.noreply.github.com>
License: Apache-2.0
License-File: LICENSE
License-File: NOTICE
Classifier: License :: OSI Approved :: Apache Software License
Classifier: Operating System :: OS Independent
Classifier: Programming Language :: Python
Classifier: Programming Language :: Python :: 3
Classifier: Programming Language :: Python :: 3.10
Classifier: Programming Language :: Python :: 3.11
Classifier: Programming Language :: Python :: 3.12
Classifier: Programming Language :: Python :: 3.13
Requires-Python: >=3.10
Requires-Dist: aws-lambda-powertools>=2.30.0
Requires-Dist: bs4>=0.0.2
Requires-Dist: httpx>=0.27.0
Requires-Dist: mcp[cli]>=1.23.0
Requires-Dist: pydantic>=2.10.6
